LICENSE.rst
MANIFEST.in
README.rst
arduinoserial.py
setup.py
test_arduinoserial.py
arduinoserial.egg-info/PKG-INFO
arduinoserial.egg-info/SOURCES.txt
arduinoserial.egg-info/dependency_links.txt
arduinoserial.egg-info/requires.txt
arduinoserial.egg-info/top_level.txt