Metadata-Version: 1.1
Name: arduinoserial
Version: 1.0.1
Summary: A Python interface to Arduino serial ports.
Home-page: https://github.com/wiseman/arduino-serial
Author: John Wiseman
Author-email: jjwiseman@gmail.com
License: MIT
Keywords: nlp nlu naturallanguage text classification development
Platform: UNKNOWN
Classifier: Development Status :: 4 - Beta
Classifier: Intended Audience :: Developers
Classifier: License :: OSI Approved :: MIT License
Classifier: Programming Language :: Python :: 2
Classifier: Programming Language :: Python :: 2.6
Classifier: Programming Language :: Python :: 2.7
Classifier: Programming Language :: Python :: 3
Classifier: Programming Language :: Python :: 3.2
Classifier: Programming Language :: Python :: 3.3
Classifier: Programming Language :: Python :: 3.4
Classifier: Programming Language :: Python :: 3.5
